lakeformation/__init__.py
lakeformation/_version.py
lakeformation/abstract.py
lakeformation/boto_utils.py
lakeformation/constant.py
lakeformation/exc.py
lakeformation/gen_code.py
lakeformation/logger.py
lakeformation/permission.py
lakeformation/principal.py
lakeformation/resource.py
lakeformation/runtime.py
lakeformation/utils.py
lakeformation/validator.py
lakeformation/__pycache__/__init__.cpython-38.pyc
lakeformation/__pycache__/__init__.cpython-39.pyc
lakeformation/__pycache__/_version.cpython-38.pyc
lakeformation/__pycache__/_version.cpython-39.pyc
lakeformation/__pycache__/abstract.cpython-38.pyc
lakeformation/__pycache__/boto_utils.cpython-38.pyc
lakeformation/__pycache__/constant.cpython-38.pyc
lakeformation/__pycache__/exc.cpython-38.pyc
lakeformation/__pycache__/gen_code.cpython-38.pyc
lakeformation/__pycache__/logger.cpython-38.pyc
lakeformation/__pycache__/permission.cpython-38.pyc
lakeformation/__pycache__/principal.cpython-38.pyc
lakeformation/__pycache__/resource.cpython-38.pyc
lakeformation/__pycache__/runtime.cpython-38.pyc
lakeformation/__pycache__/utils.cpython-38.pyc
lakeformation/__pycache__/validator.cpython-38.pyc
lakeformation/docs/__init__.py
lakeformation/docs/__pycache__/__init__.cpython-38.pyc
lakeformation/pb/__init__.py
lakeformation/pb/asso.py
lakeformation/pb/playbook.py
lakeformation/pb/__pycache__/__init__.cpython-38.pyc
lakeformation/pb/__pycache__/asso.cpython-38.pyc
lakeformation/pb/__pycache__/playbook.cpython-38.pyc
lakeformation/tests/__init__.py
lakeformation/tests/__pycache__/__init__.cpython-38.pyc
lakeformation/tpl/README.rst
lakeformation/tpl/principal.tpl
lakeformation/tpl/resource.tpl
lakeformation-0.0.2.dist-info/AUTHORS.rst
lakeformation-0.0.2.dist-info/LICENSE.txt
lakeformation-0.0.2.dist-info/METADATA
lakeformation-0.0.2.dist-info/WHEEL
lakeformation-0.0.2.dist-info/top_level.txt
lakeformation-0.0.2.dist-info/RECORD
